mkdocs_git_timeline_plugin/__init__.py
mkdocs_git_timeline_plugin/ci.py
mkdocs_git_timeline_plugin/exclude.py
mkdocs_git_timeline_plugin/plugin.py
mkdocs_git_timeline_plugin/util.py
mkdocs_git_timeline_plugin/git/__init__.py
mkdocs_git_timeline_plugin/git/author.py
mkdocs_git_timeline_plugin/git/command.py
mkdocs_git_timeline_plugin/git/commit.py
mkdocs_git_timeline_plugin/git/page.py
mkdocs_git_timeline_plugin/git/repo.py
mkdocs_git_timeline_plugin/git/timeknots/__init__.py
mkdocs_git_timeline_plugin-0.0.8.dist-info/LICENSE
mkdocs_git_timeline_plugin-0.0.8.dist-info/METADATA
mkdocs_git_timeline_plugin-0.0.8.dist-info/WHEEL
mkdocs_git_timeline_plugin-0.0.8.dist-info/entry_points.txt
mkdocs_git_timeline_plugin-0.0.8.dist-info/top_level.txt
mkdocs_git_timeline_plugin-0.0.8.dist-info/RECORD
