Metadata-Version: 2.1
Name: mkdocs-git-timeline-plugin
Version: 0.0.8
Summary: Mkdocs plugin to display git timeline of a page
Home-page: https://github.com/timvink/mkdocs-git-timeline-plugin
Author: Tim Vink, Franciszek Piszcz
Author-email: vinktim@gmail.com, franek.piszcz@gmail.com
License: MIT
Keywords: mkdocs git timeline contributors committers authors plugin
Classifier: Operating System :: OS Independent
Classifier: Programming Language :: Python
Classifier: Programming Language :: Python :: 3
Classifier: Programming Language :: Python :: 3.7
Classifier: Programming Language :: Python :: 3.8
Classifier: Programming Language :: Python :: 3.9
Classifier: Programming Language :: Python :: 3.10
Classifier: Programming Language :: Python :: 3 :: Only
Classifier: License :: OSI Approved :: MIT License
Classifier: Topic :: Documentation
Classifier: Topic :: Text Processing
Requires-Python: >=3.6
License-File: LICENSE
Requires-Dist: mkdocs (>=1.0)
